RenderCat/__init__.py
RenderCat/camera.py
RenderCat/light.py
RenderCat/loadobject.py
RenderCat/mesh.py
RenderCat/model.py
RenderCat/scene.py
RenderCat/scene_renderer.py
RenderCat/shader_program.py
RenderCat/texture.py
RenderCat/vao.py
RenderCat/vbo.py
rendercat-1.0.1.dist-info/LICENSE
rendercat-1.0.1.dist-info/METADATA
rendercat-1.0.1.dist-info/WHEEL
rendercat-1.0.1.dist-info/top_level.txt
rendercat-1.0.1.dist-info/RECORD
